Workbook

Sheet GESTIONE
C2: BAR 1 | I2: BAR PREMIUM | O2: CAMBUSA 1 | T2: CONTANTE PRELEVATO
C3: TIPOLOGIA | D3: PREZZO | E3: N° | F3: TOTALI | I3: TIPOLOGIA | J3: PREZZO | K3: N° | L3: TOTALI | O3: CONTANTE | P3: SOSPESO | Q3: POS | R3: TOTALE | T3: =E10+E11+E12+E13+Q5+Q6+Q7+Q8+Q9+Q10+Q11+Q32+Q33+Q34+Q35+Q36+Q37+Q38+E37+E38+E39+E40 -> 0
C4: I CONSUMAZIONE | D4: 15 | E4: 0 | F4: =D4*E4 -> 0 | I4: I CONSUMAZIONE | J4: 15 | K4: 0 | L4: =J4*K4 -> 0 | O4: 0 | P4: 0 | Q4: 0 | R4: =O4+P4+Q4 -> 0
C5: ACQUA | D5: 3 | E5: 0 | F5: =D5*E5 -> 0 | I5: ACQUA | J5: 3 | K5: 0 | L5: =J5*K5 -> 0 | O5: PRELIEVO 1 | Q5: 0 | T5: SPESE PAGATE
C6: II CONSUMAZIONE | D6: 10 | E6: 0 | F6: =D6*E6 -> 0 | I6: II CONSUMAZIONE | J6: 10 | K6: 0 | L6: =J6*K6 -> 0 | O6: PRELIEVO 2 | Q6: 0 | T6: =F76+F77+F105+K105+L91+E79+(E74-D56) -> 4040
C7: CICCHETTO | D7: 5 | E7: 0 | F7: =D7*E7 -> 0 | I7: CICCHETTO | J7: 5 | K7: 0 | L7: =J7*K7 -> 0 | O7: PRELIEVO 3 | Q7: 0
C8: PREMIUM | D8: 15 | E8: 0 | F8: =D8*E8 -> 0 | I8: PREMIUM | J8: 15 | K8: 0 | L8: =J8*K8 -> 0 | O8: POS | Q8: 0 | T8: RIMANENZA CASH
C9: INGRESSO TAVOLO | D9: 20 | E9: 0 | F9: =D9*E9 -> 0 | I9: INGRESSO TAVOLO | J9: 20 | K9: 0 | L9: =J9*K9 -> 0 | O9: SOSPESO | Q9: 0 | T9: =T3-T6-Q4-Q31-D15-D42 -> -4040
C10: PRELIEVO 1 | E10: 0 | I10: PRELIEVO 1 | K10: 0 | O10: PRELIEVO 6 | Q10: 0
C11: PRELIEVO 2 | E11: 0 | I11: PRELIEVO 2 | K11: 0 | O11: PRELIEVO 7 | Q11: 0
C12: PRELIEVO 3 | E12: 0 | I12: PRELIEVO 3 | K12: 0 | O12: SALDO | Q12: =R4-Q5-Q9-Q10-Q11-Q6-Q7-Q8 -> 0
C13: POS | E13: 0 | I13: PRELIEVO 4 | K13: 0
C14: SALDO | E14: =E15-E10-E11-E12-E13 -> 0 | I14: SALDO | K14: =K15-K10-K11-K12-K13 -> 0
C15: Di cui POS | D15: =E13 -> 0 | E15: =SUM(F4:F9) -> 0 | I15: Di cui POS | J15: 0 | K15: =SUM(L4:L9) -> 0
C17: BAR LATERALE | I17: BOTTEGHINO LISTA 2 | O17: TAVOLI CAMBUSA CENTRALE LAURA
C18: TIPOLOGIA | D18: PREZZO | E18: N° | F18: TOTALI | I18: CARD 10 | J18: 10 | L18: =J18*K18 -> 0 | O18: CONTANTE | P18: SOSPESO | Q18: POS | R18: TOTALE
C19: I CONSUMAZIONE | D19: 15 | F19: =D19*E19 -> 0 | I19: CARD 15 | J19: 15 | L19: =J19*K19 -> 0 | O19: 0 | P19: 0 | Q19: 0 | R19: =O19+P19+Q19 -> 0
C20: II CONSUMAZIONE | D20: 10 | F20: =D20*E20 -> 0 | I20: CARD 20 | J20: 20 | L20: =J20*K20 -> 0 | O20: PRELIEVO 1 | Q20: 0
C21: ACQUA | D21: 3 | F21: =D21*E21 -> 0 | I21: CARD 25 | J21: 25 | L21: =J21*K21 -> 0 | O21: PRELIEVO 2 | Q21: 0
C22: PRELIEVO 1 | E22: 0 | I22: PRELIEVO 1 | K22: 0 | O22: PRELIEVO 3 | Q22: 0
C23: PRELIEVO 2 | E23: 0 | I23: PRELIEVO 2 | K23: 0 | O23: PRELIEVO 4 | Q23: 0
C24: PRELIEVO 3 | E24: 0 | I24: PRELIEVO 3 | K24: 0 | O24: SALDO | Q24: =R19-Q20-Q21-Q22-Q23 -> 0
C25: PRELIEVO 4 | E25: 0 | I25: PRELIEVO 4 | K25: 0
C26: SALDO | E26: =E27-E25-E24-E23-E22 -> 0 | I26: SALDO | K26: =K27-K25-K24-K23-K22 -> 0
C27: Di cui POS | D27: 0 | E27: =SUM(F19:F21) -> 0 | I27: Di cui POS | J27: 0 | K27: =L18+L19+L20+L21 -> 0
C29: BAR 2 | I29: BOTTEGHINO TAVOLI 1 MARIA | O29: CAMBUSA 2
C30: TIPOLOGIA | D30: PREZZO | E30: N° | F30: TOTALI | I30: CONTANTE | J30: SOSPESO | K30: POS | L30: TOTALE | O30: CONTANTE | P30: SOSPESO | Q30: POS | R30: TOTALE
C31: I CONSUMAZIONE | D31: 20 | E31: 0 | F31: =D31*E31 -> 0 | L31: =I31+J31+K31 -> 0 | O31: 0 | P31: 0 | Q31: 0 | R31: =O31+P31+Q31 -> 0
C32: ACQUA | D32: 3 | E32: 0 | F32: =D32*E32 -> 0 | O32: PRELIEVO 1 | Q32: 0
C33: I e II CONSUMAZIONE | D33: 10 | E33: 0 | F33: =D33*E33 -> 0 | O33: PRELIEVO 2 | Q33: 0
C34: CICCHETTO | D34: 5 | E34: 0 | F34: =D34*E34 -> 0 | O34: PRELIEVO 3 | Q34: 0
C35: PREMIUM | D35: 15 | E35: 0 | F35: =D35*E35 -> 0 | I35: PRELIEVO 1 | K35: 0 | O35: PRELIEVO 4 | Q35: 0
C36: INGRESSO TVL | D36: 30 | E36: 0 | F36: =D36*E36 -> 0 | I36: PRELIEVO 2 | K36: 0 | O36: PRELIEVO 5 | Q36: 0
C37: PRELIEVO 1 | E37: 0 | I37: PRELIEVO 3 | K37: 0 | O37: PRELIEVO 6 | Q37: 0
C38: PRELIEVO 2 | E38: 0 | I38: PRELIEVO 4 | K38: 0 | O38: PRELIEVO 7 | Q38: 0
C39: POS | E39: 0 | I39: SALDO | K39: =L31-K35-K36-K37-K38 -> 0 | O39: SALDO | Q39: =R31-Q32-Q33-Q34-Q35-Q36-Q37-Q38 -> 0
C40: ONLINE | E40: 0
C41: SALDO | E41: =E42-E40-E39-E38-E37 -> 0
C42: Di cui POS | D42: =E39 -> 0 | E42: =SUM(F31:F36) -> 0
C44: INCASSO | I44: INCASSO | J44: =D57 -> 0 | L44: GRANDI VOCI | O44: CONSUMATO TAVOLI
C45: BAR 1 | D45: =E15 -> 0 | I45: ARTISTICO | J45: =L91 -> 0 | L45: UTILE NONAME | O45: ABSOLUT | P45: 14 | Q45: 0 | R45: =P45*Q45 -> 0
D46: =E27 -> 0 | I46: CONSUMATO | J46: =E79 -> 0 | L46: =J47 -> 0 | O46: BELVEDERE 0,7 | P46: 38 | Q46: 0 | R46: =P46*Q46 -> 0
C47: BAR 2 | D47: =E42 -> 0 | I47: NETTO PROPRIETA' | J47: =E74 -> 0 | L47: UTILE GESTIONE | O47: BELVEDERE 1,75L | P47: 98 | Q47: 0 | R47: =P47*Q47 -> 0
C48: BAR 3 | D48: =K15 -> 0 | I48: PERSONALE | J48: =F105 -> 2815 | L48: =J53 -> -4040 | O48: BELUGA NIGHT | P48: 52 | Q48: 0 | R48: =P48*Q48 -> 0
D49: =K27 -> 0 | I49: PULIZIE | J49: =F76 -> 500 | L49: SPESE TOTALI | O49: VDK FRUTTA | P49: 13 | Q49: 0 | R49: =P49*Q49 -> 0
D50: =L31 -> 0 | I50: SIAE | J50: =F77 -> 500 | L50: =J45+J46+J48+J49+J50+J51+E74 -> 4040 | O50: BELVEDERE 3L | P50: 230 | Q50: 0 | R50: =P50*Q50 -> 0
C51: CAMBUSA 1 | D51: =R4 -> 0 | I51: SPESE TECNICHE | J51: =K105 -> 225 | L51: ARTISTICO | O51: TANQUERAY TEN | P51: 21 | Q51: 0 | R51: =P51*Q51 -> 0
D52: =R19 -> 0 | I52: SOSPESI TVL | J52: =D54 -> 0 | L52: =J45 -> 0 | O52: MALFY | P52: 36 | Q52: 0 | R52: =P52*Q52 -> 0
C53: CAMBUSA 2 | D53: =R31 -> 0 | I53: LORDO GESTIONE | J53: =D57-J45-J46-J48-J49-J50-J51-E74 -> -4040 | O53: GIN MARE | P53: 38 | Q53: 0 | R53: =P53*Q53 -> 0
C54: SOSPESO TAVOLI | D54: =P31+P4 -> 0 | O54: MUMM 0,70 | P54: 37 | Q54: 0 | R54: =P54*Q54 -> 0
C55: GUARDAROBA | O55: MUMM 1,50 | P55: 87 | Q55: 0 | R55: =P55*Q55 -> 0
C56: POS | D56: =D42+D15+Q4+Q31 -> 0 | I56: DRINK OMAGGIO | O56: MOET 0,70 | P56: 44 | Q56: 0 | R56: =P56*Q56 -> 0
C57: Incasso Totale | D57: =SUM(D45:D53)+D55 -> 0 | I57: TICKET | L57: 0 | O57: MOET ICE 0,70 | P57: 60 | Q57: 0 | R57: =P57*Q57 -> 0
I58: A VOCE | O58: MOET ICE 1,50 | P58: 160 | Q58: 0 | R58: =P58*Q58 -> 0
I59: ACQUA | L59: 0 | O59: MOET NIR | P59: 95 | Q59: 0 | R59: =P59*Q59 -> 0
O60: MOET NIR 1,5 | P60: 292 | Q60: 0 | R60: =P60*Q60 -> 0
O61: CRISTAL 0,75 | P61: 190 | Q61: 0 | R61: =P61*Q61 -> 0
O62: DOMPERIGNON 0,70 | P62: 210 | Q62: 0 | R62: =P62*Q62 -> 0
O63: BERLUCCHI | P63: 11 | Q63: 0 | R63: =P63*Q63 -> 0
O64: ARMAND DE BRIGNAC | P64: 240 | Q64: 0 | R64: =P64*Q64 -> 0
O65: ALTOS | P65: 38 | Q65: 0 | R65: =P65*Q65 -> 0
O66: CASAMIGOS | P66: 44 | Q66: 0 | R66: =P66*Q66 -> 0
O67: SAMBUCA | P67: 16 | Q67: 0 | R67: =P67*Q67 -> 0
O68: PROSECCO | P68: 6 | Q68: 0 | R68: =P68*Q68 -> 0
O69: USCITA VODKA | P69: 10 | Q69: 0 | R69: =P69*Q69 -> 0
O70: USCITA RUM | P70: 8 | Q70: 0 | R70: =P70*Q70 -> 0
O71: Consumato Tavoli | Q71: =SUM(Q45:Q68) -> 0 | R71: =SUM(R45:R70) -> 0
I72: SPESE ARTISTICHE
I73: TIPOLOGIA | K73: NUM. | L73: TOT COSTO
C74: FITTO-ACCORDO | E74: =(D57/100)*50 -> 0
O75: LA GESTIONE DEVE AVERE IN CASH
C76: PULIZIE | F76: 500 | O76: =J53-J52 -> -4040
C77: SIAE | F77: 500
O78: A CUI VA AGGIUNTO | P78: =J52 -> 0 | Q78: DI SOSPESO
C79: CONSUMATO | E79: =F80+F81+F82 -> 0
C80: CONSUMATO BAR | F80: =(E4+E6+E31+E33+K6)*1.6+(E5+E7+E32+E34+K5+K7+L59)*1+(E8+E35+K8)*5+(L57+L58)*1.6 -> 0
C81: CONSUMATO TAVOLI | F81: =R71 -> 0
C83: SPESE DEL PERSONALE
C84: MANSIONE | D84: COSTO | E84: N° | F84: TOTALE
C85: SICUREZZA PS | D85: 180 | E85: 2 | F85: =D85*E85 -> 360
C86: SICUREZZA Agenzia | D86: 135 | E86: 2 | F86: =D86*E86 -> 270
C87: STACCO | D87: 135 | E87: 1 | F87: =D87*E87 -> 135
C88: SUPPORTO SICUREZZA E VIABILITA' | D88: 165 | E88: 1 | F88: =D88*E88 -> 165
C89: TOTALE SICUREZZA | E89: =SUM(F85:F88) -> 930
C90: DIRETTORE | D90: 150 | E90: 1 | F90: =D90*E90 -> 150
C91: PALMARE | D91: 90 | E91: 2 | F91: =D91*E91 -> 180 | I91: Totale Spese Artistiche | L91: =SUM(L74:L90) -> 0
C92: CAMBUSIERE | D92: 90 | E92: 1 | F92: =D92*E92 -> 90
C93: TOTALE SALA | E93: =F90+F91+F92 -> 420 | I93: SPESE TECNICHE
C94: RESPONSABILE BAR | D94: 150 | E94: 1 | F94: =D94*E94 -> 150 | I94: VJ | L94: 225
C95: BARMAN | D95: 110 | E95: 3 | F95: =D95*E95 -> 330 | I95: CO2
C96: BARBACK | D96: 75 | E96: 1 | F96: =D96*E96 -> 75
C97: TOTALE BAR | E97: =F94+F95+F96 -> 555
C98: BOTTEGHINO LISTA | D98: 90 | E98: 1 | F98: =D98*E98 -> 90
C99: BOTTEGHINO TAVOLI | D99: 90 | E99: 1 | F99: =D99*E99 -> 90
C100: BAR | D100: 90 | E100: 1 | F100: =D100*E100 -> 90
C101: TOTALE CASSE | E101: =SUM(F98:F100) -> 270
C102: CEDOLINI | D102: 25 | E102: 10 | F102: =D102*E102 -> 250
C103: LAVAGGIO | D103: 80 | E103: 3 | F103: =D103*E103 -> 240
C104: BAGNI | D104: 75 | E104: 2 | F104: =D104*E104 -> 150
C105: Totale Spese del Personale | F105: =SUM(E89+E93+E97+E101+F102+F103+F104) -> 2815 | I105: Totale Spese Gestione | K105: =SUM(L94:L104) -> 225

Sheet GUARDAROBA
A1: GUARDAROBA | B1: N° | C1: COSTO | D1: TOTALE
A3: CAPO €5 | B3: 0 | C3: 5 | D3: =B3*C3 -> 0
A4: CAPO €2 | B4: 0 | C4: 2 | D4: =B4*C4 -> 0
C5: TOTALE | D5: =D3+D4 -> 0
A8: PERSONALE
A9: OPERATORE | B9: 5 | C9: 75 | D9: =B9*C9 -> 375
A12: CASSIERE | B12: 2 | C12: 90 | D12: =B12*C12 -> 180
A14: ACCONTO | B14: 0
A15: POS | B15: 0
A16: TOTALE | B16: =B14+B15 -> 0 | C16: NETTO | D16: =D5-D9-D12 -> -555

Sheet RESOCONTO PROPRIETA
A1: RESOCONTO PROPRIETA' 01.01.25
A3: FITTO | B3: =GESTIONE!E74 -> 0
A4: CONSUMATO TOTALE | B4: =GESTIONE!E79 -> 0
A5: NETTO GUARDAROBA | B5: =GUARDAROBA!D16 -> -555
A6: PULIZIE | B6: 500
A7: SIAE | B7: 500
A8: CEDOLINI | B8: 250
A9: CONTABILITA' | B9: 0
A10: ASSUNZIONI SICUREZZA | B10: 0
A11: BONIFICI PERSONALE | B11: 0
A12: COMUNICAZIONE | B12: 0
B21: =SUM(B3:B19) -> 695
A23: RIENTRI E ACCONTI
A25: POS SERATA | B25: =GESTIONE!D56 -> 0
A26: DIREZIONE | B26: 0
A27: POS GUARDAROBA | B27: 0
A28: ONLINE | B28: 0
B32: =SUM(B25:B30) -> 0
A34: RESIDUO CONTANTE | B34: =B21-B32 -> 695

Sheet PRESENZE PERSONALE
A1: 01.01.2025
D34: TOTALE | E34: ='RESOCONTO PROPRIETA'!B11 -> 0
